{
    "@schema": "https://raw.githubusercontent.com/slicer/slicer/master/Modules/Loadable/Markups/Resources/Schema/markups-schema-v1.0.3.json#",
    "markups": [
        {
            "type": "Curve",
            "coordinateSystem": "LPS",
            "coordinateUnits": "mm",
            "locked": false,
            "fixedNumberOfControlPoints": false,
            "labelFormat": "%N-%d",
            "lastUsedControlPointNumber": 15,
            "controlPoints": [
                {
                    "id": "3",
                    "label": "SplineAnt_ma-3",
                    "description": "",
                    "associatedNodeID": "",
                    "position": [-9.08067798614502, 9.987853050231934, -169.02796936035156],
                    "orientation": [-1.0, -0.0, -0.0, -0.0, -1.0, -0.0, 0.0, 0.0, 1.0],
                    "selected": true,
                    "locked": false,
                    "visibility": true,
                    "positionStatus": "defined"
                },
                {
                    "id": "4",
                    "label": "SplineAnt_ma-4",
                    "description": "",
                    "associatedNodeID": "",
                    "position": [-8.129801750183105, 8.652355194091797, -165.05274963378906],
                    "orientation": [-1.0, -0.0, -0.0, -0.0, -1.0, -0.0, 0.0, 0.0, 1.0],
                    "selected": true,
                    "locked": false,
                    "visibility": true,
                    "positionStatus": "defined"
                },
                {
                    "id": "5",
                    "label": "SplineAnt_ma-5",
                    "description": "",
                    "associatedNodeID": "",
                    "position": [-7.313805103302002, 6.26335334777832, -156.8273468017578],
                    "orientation": [-1.0, -0.0, -0.0, -0.0, -1.0, -0.0, 0.0, 0.0, 1.0],
                    "selected": true,
                    "locked": false,
                    "visibility": true,
                    "positionStatus": "defined"
                },
                {
                    "id": "6",
                    "label": "SplineAnt_ma-6",
                    "description": "",
                    "associatedNodeID": "",
                    "position": [-6.4643049240112305, 4.178112030029297, -149.54063415527344],
                    "orientation": [-1.0, -0.0, -0.0, -0.0, -1.0, -0.0, 0.0, 0.0, 1.0],
                    "selected": true,
                    "locked": false,
                    "visibility": true,
                    "positionStatus": "defined"
                },
                {
                    "id": "7",
                    "label": "SplineAnt_ma-7",
                    "description": "",
                    "associatedNodeID": "",
                    "position": [-4.962178707122803, 1.1097999811172483, -137.74478149414065],
                    "orientation": [-1.0, -0.0, -0.0, -0.0, -1.0, -0.0, 0.0, 0.0, 1.0],
                    "selected": true,
                    "locked": false,
                    "visibility": true,
                    "positionStatus": "defined"
                },
                {
                    "id": "8",
                    "label": "SplineAnt_ma-8",
                    "description": "",
                    "associatedNodeID": "",
                    "position": [-2.951206684112549, 0.1647704541683197, -125.99266815185548],
                    "orientation": [-1.0, -0.0, -0.0, -0.0, -1.0, -0.0, 0.0, 0.0, 1.0],
                    "selected": true,
                    "locked": false,
                    "visibility": true,
                    "positionStatus": "defined"
                },
                {
                    "id": "9",
                    "label": "SplineAnt_ma-9",
                    "description": "",
                    "associatedNodeID": "",
                    "position": [-1.697492599487305, 0.8426730632781982, -110.85541534423828],
                    "orientation": [-1.0, -0.0, -0.0, -0.0, -1.0, -0.0, 0.0, 0.0, 1.0],
                    "selected": true,
                    "locked": false,
                    "visibility": true,
                    "positionStatus": "defined"
                },
                {
                    "id": "10",
                    "label": "SplineAnt_ma-10",
                    "description": "",
                    "associatedNodeID": "",
                    "position": [-2.7732787132263184, 4.071883678436279, -99.00214385986328],
                    "orientation": [-1.0, -0.0, -0.0, -0.0, -1.0, -0.0, 0.0, 0.0, 1.0],
                    "selected": true,
                    "locked": false,
                    "visibility": true,
                    "positionStatus": "defined"
                },
                {
                    "id": "11",
                    "label": "SplineAnt_ma-11",
                    "description": "",
                    "associatedNodeID": "",
                    "position": [-4.99101448059082, 9.946537017822266, -84.86834716796875],
                    "orientation": [-1.0, -0.0, -0.0, -0.0, -1.0, -0.0, 0.0, 0.0, 1.0],
                    "selected": true,
                    "locked": false,
                    "visibility": true,
                    "positionStatus": "defined"
                },
                {
                    "id": "12",
                    "label": "SplineAnt_ma-12",
                    "description": "",
                    "associatedNodeID": "",
                    "position": [-6.315680980682373, 15.485180854797363, -67.62124633789063],
                    "orientation": [-1.0, -0.0, -0.0, -0.0, -1.0, -0.0, 0.0, 0.0, 1.0],
                    "selected": true,
                    "locked": false,
                    "visibility": true,
                    "positionStatus": "defined"
                },
                {
                    "id": "13",
                    "label": "SplineAnt_ma-13",
                    "description": "",
                    "associatedNodeID": "",
                    "position": [-6.973511219024658, 16.038110733032227, -53.820255279541016],
                    "orientation": [-1.0, -0.0, -0.0, -0.0, -1.0, -0.0, 0.0, 0.0, 1.0],
                    "selected": true,
                    "locked": false,
                    "visibility": true,
                    "positionStatus": "defined"
                },
                {
                    "id": "14",
                    "label": "SplineAnt_ma-14",
                    "description": "",
                    "associatedNodeID": "",
                    "position": [-9.889617919921877, 15.697166442871094, -37.772891998291016],
                    "orientation": [-1.0, -0.0, -0.0, -0.0, -1.0, -0.0, 0.0, 0.0, 1.0],
                    "selected": true,
                    "locked": false,
                    "visibility": true,
                    "positionStatus": "defined"
                },
                {
                    "id": "15",
                    "label": "SplineAnt_ma-15",
                    "description": "",
                    "associatedNodeID": "",
                    "position": [-14.313006401062012, 14.164874076843262, -25.348194122314453],
                    "orientation": [-1.0, -0.0, -0.0, -0.0, -1.0, -0.0, 0.0, 0.0, 1.0],
                    "selected": true,
                    "locked": false,
                    "visibility": true,
                    "positionStatus": "defined"
                }
            ],
            "measurements": [
                {
                    "name": "length",
                    "enabled": false,
                    "units": "mm",
                    "printFormat": "%-#4.4g%s"
                },
                {
                    "name": "curvature mean",
                    "enabled": false,
                    "printFormat": "%5.3f %s"
                },
                {
                    "name": "curvature max",
                    "enabled": false,
                    "printFormat": "%5.3f %s"
                },
                {
                    "name": "torsion mean",
                    "enabled": false,
                    "printFormat": "%5.3f %s"
                },
                {
                    "name": "torsion max",
                    "enabled": false,
                    "printFormat": "%5.3f %s"
                }
            ],
            "display": {
                "visibility": true,
                "opacity": 1.0,
                "color": [0.4, 1.0, 1.0],
                "selectedColor": [1.0, 0.500008, 0.500008],
                "activeColor": [0.4, 1.0, 0.0],
                "propertiesLabelVisibility": true,
                "pointLabelsVisibility": false,
                "textScale": 3.0,
                "glyphType": "Sphere3D",
                "glyphScale": 3.0,
                "glyphSize": 5.0,
                "useGlyphScale": true,
                "sliceProjection": false,
                "sliceProjectionUseFiducialColor": true,
                "sliceProjectionOutlinedBehindSlicePlane": false,
                "sliceProjectionColor": [1.0, 1.0, 1.0],
                "sliceProjectionOpacity": 0.6,
                "lineThickness": 0.2,
                "lineColorFadingStart": 1.0,
                "lineColorFadingEnd": 10.0,
                "lineColorFadingSaturation": 1.0,
                "lineColorFadingHueOffset": 0.0,
                "handlesInteractive": false,
                "translationHandleVisibility": true,
                "rotationHandleVisibility": true,
                "scaleHandleVisibility": true,
                "interactionHandleScale": 3.0,
                "snapMode": "toVisibleSurface"
            }
        }
    ]
}